{
  "current": "GROW",
  "history": [
    {
      "directive": "GROW",
      "avg_score": 548.5,
      "timestamp": "2026-02-28T20:19:26.153843"
    },
    {
      "directive": "GROW",
      "avg_score": 548.5,
      "timestamp": "2026-02-28T20:19:31.214963"
    },
    {
      "directive": "GROW",
      "avg_score": 548.5,
      "timestamp": "2026-02-28T20:19:36.020524"
    },
    {
      "directive": "GROW",
      "avg_score": 548.5,
      "timestamp": "2026-02-28T20:19:40.785698"
    },
    {
      "directive": "GROW",
      "avg_score": 548.5,
      "timestamp": "2026-02-28T20:19:45.539094"
    },
    {
      "directive": "GROW",
      "avg_score": 548.5,
      "timestamp": "2026-02-28T20:19:50.320398"
    },
    {
      "directive": "GROW",
      "avg_score": 548.5,
      "timestamp": "2026-02-28T20:19:55.150472"
    },
    {
      "directive": "GROW",
      "avg_score": 548.5,
      "timestamp": "2026-02-28T20:20:00.063265"
    },
    {
      "directive": "GROW",
      "avg_score": 548.5,
      "timestamp": "2026-02-28T20:20:05.003208"
    },
    {
      "directive": "GROW",
      "avg_score": 548.5,
      "timestamp": "2026-02-28T20:20:09.771181"
    },
    {
      "directive": "GROW",
      "avg_score": 548.5,
      "timestamp": "2026-02-28T20:20:14.519777"
    },
    {
      "directive": "GROW",
      "avg_score": 548.5,
      "timestamp": "2026-02-28T20:20:19.282964"
    },
    {
      "directive": "GROW",
      "avg_score": 548.5,
      "timestamp": "2026-02-28T20:20:24.067504"
    },
    {
      "directive": "GROW",
      "avg_score": 548.5,
      "timestamp": "2026-02-28T20:20:28.821734"
    },
    {
      "directive": "GROW",
      "avg_score": 548.5,
      "timestamp": "2026-02-28T20:20:33.563461"
    },
    {
      "directive": "GROW",
      "avg_score": 548.5,
      "timestamp": "2026-02-28T20:20:38.315205"
    },
    {
      "directive": "GROW",
      "avg_score": 548.5,
      "timestamp": "2026-02-28T20:20:43.072528"
    },
    {
      "directive": "GROW",
      "avg_score": 548.5,
      "timestamp": "2026-02-28T20:20:47.850450"
    },
    {
      "directive": "GROW",
      "avg_score": 548.5,
      "timestamp": "2026-02-28T20:20:52.636129"
    },
    {
      "directive": "GROW",
      "avg_score": 548.5,
      "timestamp": "2026-02-28T20:20:57.429665"
    },
    {
      "directive": "GROW",
      "avg_score": 548.5,
      "timestamp": "2026-02-28T20:21:03.208202"
    },
    {
      "directive": "GROW",
      "avg_score": 548.5,
      "timestamp": "2026-02-28T20:21:07.993673"
    },
    {
      "directive": "GROW",
      "avg_score": 548.5,
      "timestamp": "2026-02-28T20:21:12.813449"
    },
    {
      "directive": "GROW",
      "avg_score": 548.5,
      "timestamp": "2026-02-28T20:21:17.648836"
    },
    {
      "directive": "GROW",
      "avg_score": 548.5,
      "timestamp": "2026-02-28T20:21:22.459836"
    },
    {
      "directive": "GROW",
      "avg_score": 548.5,
      "timestamp": "2026-02-28T20:21:27.283835"
    },
    {
      "directive": "GROW",
      "avg_score": 548.5,
      "timestamp": "2026-02-28T20:21:32.094638"
    },
    {
      "directive": "GROW",
      "avg_score": 548.5,
      "timestamp": "2026-02-28T20:21:36.907700"
    },
    {
      "directive": "GROW",
      "avg_score": 548.5,
      "timestamp": "2026-02-28T20:21:41.819500"
    },
    {
      "directive": "GROW",
      "avg_score": 548.5,
      "timestamp": "2026-02-28T20:21:46.768932"
    },
    {
      "directive": "GROW",
      "avg_score": 548.5,
      "timestamp": "2026-02-28T20:21:51.625445"
    },
    {
      "directive": "GROW",
      "avg_score": 548.5,
      "timestamp": "2026-02-28T20:21:56.545749"
    },
    {
      "directive": "GROW",
      "avg_score": 548.5,
      "timestamp": "2026-02-28T20:22:01.466287"
    },
    {
      "directive": "GROW",
      "avg_score": 548.5,
      "timestamp": "2026-02-28T20:22:06.356304"
    },
    {
      "directive": "GROW",
      "avg_score": 548.5,
      "timestamp": "2026-02-28T20:22:11.238591"
    },
    {
      "directive": "GROW",
      "avg_score": 548.5,
      "timestamp": "2026-02-28T20:22:16.146687"
    },
    {
      "directive": "GROW",
      "avg_score": 548.5,
      "timestamp": "2026-02-28T20:22:21.067919"
    },
    {
      "directive": "GROW",
      "avg_score": 548.5,
      "timestamp": "2026-02-28T20:22:25.981522"
    },
    {
      "directive": "GROW",
      "avg_score": 548.5,
      "timestamp": "2026-02-28T20:22:30.899070"
    },
    {
      "directive": "GROW",
      "avg_score": 548.5,
      "timestamp": "2026-02-28T20:22:35.866020"
    },
    {
      "directive": "GROW",
      "avg_score": 548.5,
      "timestamp": "2026-02-28T20:22:41.881711"
    },
    {
      "directive": "GROW",
      "avg_score": 548.5,
      "timestamp": "2026-02-28T20:22:46.897067"
    },
    {
      "directive": "GROW",
      "avg_score": 548.5,
      "timestamp": "2026-02-28T20:22:51.843716"
    },
    {
      "directive": "GROW",
      "avg_score": 548.5,
      "timestamp": "2026-02-28T20:22:56.835227"
    },
    {
      "directive": "GROW",
      "avg_score": 548.5,
      "timestamp": "2026-02-28T20:23:01.793900"
    },
    {
      "directive": "GROW",
      "avg_score": 548.5,
      "timestamp": "2026-02-28T20:23:06.773750"
    },
    {
      "directive": "GROW",
      "avg_score": 548.5,
      "timestamp": "2026-02-28T20:23:11.725984"
    },
    {
      "directive": "GROW",
      "avg_score": 548.5,
      "timestamp": "2026-02-28T20:23:16.768617"
    },
    {
      "directive": "GROW",
      "avg_score": 548.5,
      "timestamp": "2026-02-28T20:23:21.761085"
    },
    {
      "directive": "GROW",
      "avg_score": 548.5,
      "timestamp": "2026-02-28T20:23:26.754103"
    },
    {
      "directive": "GROW",
      "avg_score": 548.5,
      "timestamp": "2026-02-28T20:23:31.765055"
    },
    {
      "directive": "GROW",
      "avg_score": 548.5,
      "timestamp": "2026-02-28T20:23:40.980836"
    },
    {
      "directive": "GROW",
      "avg_score": 548.5,
      "timestamp": "2026-02-28T20:23:48.415796"
    },
    {
      "directive": "GROW",
      "avg_score": 548.5,
      "timestamp": "2026-02-28T20:24:01.304197"
    },
    {
      "directive": "GROW",
      "avg_score": 548.5,
      "timestamp": "2026-02-28T20:27:21.719337"
    },
    {
      "directive": "GROW",
      "avg_score": 548.5,
      "timestamp": "2026-02-28T20:28:34.505706"
    },
    {
      "directive": "GROW",
      "avg_score": 548.5,
      "timestamp": "2026-02-28T20:28:41.606419"
    },
    {
      "directive": "GROW",
      "avg_score": 548.5,
      "timestamp": "2026-02-28T20:28:47.243196"
    },
    {
      "directive": "GROW",
      "avg_score": 548.5,
      "timestamp": "2026-02-28T20:28:55.737723"
    },
    {
      "directive": "GROW",
      "avg_score": 548.5,
      "timestamp": "2026-02-28T20:29:00.973041"
    },
    {
      "directive": "GROW",
      "avg_score": 548.5,
      "timestamp": "2026-02-28T20:29:10.706033"
    },
    {
      "directive": "GROW",
      "avg_score": 548.5,
      "timestamp": "2026-02-28T20:29:15.919398"
    },
    {
      "directive": "GROW",
      "avg_score": 548.5,
      "timestamp": "2026-02-28T20:29:21.201232"
    },
    {
      "directive": "GROW",
      "avg_score": 548.5,
      "timestamp": "2026-02-28T20:29:26.474331"
    },
    {
      "directive": "GROW",
      "avg_score": 548.5,
      "timestamp": "2026-02-28T20:29:31.778888"
    },
    {
      "directive": "GROW",
      "avg_score": 548.5,
      "timestamp": "2026-02-28T20:29:37.180747"
    },
    {
      "directive": "GROW",
      "avg_score": 548.5,
      "timestamp": "2026-02-28T20:29:42.429320"
    },
    {
      "directive": "GROW",
      "avg_score": 548.5,
      "timestamp": "2026-02-28T20:29:47.679302"
    },
    {
      "directive": "GROW",
      "avg_score": 548.5,
      "timestamp": "2026-02-28T20:29:53.054546"
    },
    {
      "directive": "GROW",
      "avg_score": 548.5,
      "timestamp": "2026-02-28T20:29:58.316547"
    },
    {
      "directive": "GROW",
      "avg_score": 548.5,
      "timestamp": "2026-02-28T20:30:03.558163"
    },
    {
      "directive": "GROW",
      "avg_score": 548.5,
      "timestamp": "2026-02-28T20:30:09.024665"
    },
    {
      "directive": "GROW",
      "avg_score": 548.5,
      "timestamp": "2026-02-28T20:30:14.377829"
    },
    {
      "directive": "GROW",
      "avg_score": 548.5,
      "timestamp": "2026-02-28T20:30:19.723751"
    },
    {
      "directive": "GROW",
      "avg_score": 548.5,
      "timestamp": "2026-02-28T20:30:25.059390"
    },
    {
      "directive": "GROW",
      "avg_score": 548.5,
      "timestamp": "2026-02-28T20:30:30.417456"
    },
    {
      "directive": "GROW",
      "avg_score": 548.5,
      "timestamp": "2026-02-28T20:30:35.714665"
    },
    {
      "directive": "GROW",
      "avg_score": 548.5,
      "timestamp": "2026-02-28T20:30:41.080345"
    },
    {
      "directive": "GROW",
      "avg_score": 548.5,
      "timestamp": "2026-02-28T20:30:46.439804"
    },
    {
      "directive": "GROW",
      "avg_score": 548.5,
      "timestamp": "2026-02-28T20:30:51.801541"
    },
    {
      "directive": "GROW",
      "avg_score": 548.5,
      "timestamp": "2026-02-28T20:30:58.315192"
    },
    {
      "directive": "GROW",
      "avg_score": 548.5,
      "timestamp": "2026-02-28T20:31:03.694215"
    },
    {
      "directive": "GROW",
      "avg_score": 548.5,
      "timestamp": "2026-02-28T20:31:09.057642"
    },
    {
      "directive": "GROW",
      "avg_score": 548.5,
      "timestamp": "2026-02-28T20:31:14.533011"
    },
    {
      "directive": "GROW",
      "avg_score": 548.5,
      "timestamp": "2026-02-28T20:31:19.930465"
    },
    {
      "directive": "GROW",
      "avg_score": 548.5,
      "timestamp": "2026-02-28T20:31:25.338492"
    },
    {
      "directive": "GROW",
      "avg_score": 548.5,
      "timestamp": "2026-02-28T20:31:30.725549"
    },
    {
      "directive": "GROW",
      "avg_score": 548.5,
      "timestamp": "2026-02-28T20:31:36.084010"
    },
    {
      "directive": "GROW",
      "avg_score": 548.5,
      "timestamp": "2026-02-28T20:31:41.484416"
    },
    {
      "directive": "GROW",
      "avg_score": 548.5,
      "timestamp": "2026-02-28T20:31:46.880796"
    },
    {
      "directive": "GROW",
      "avg_score": 548.5,
      "timestamp": "2026-02-28T20:31:52.286802"
    },
    {
      "directive": "GROW",
      "avg_score": 548.5,
      "timestamp": "2026-02-28T20:31:57.676517"
    },
    {
      "directive": "GROW",
      "avg_score": 548.5,
      "timestamp": "2026-02-28T20:32:03.099548"
    },
    {
      "directive": "GROW",
      "avg_score": 548.5,
      "timestamp": "2026-02-28T20:32:08.533893"
    },
    {
      "directive": "GROW",
      "avg_score": 548.5,
      "timestamp": "2026-02-28T20:32:13.979816"
    },
    {
      "directive": "GROW",
      "avg_score": 548.5,
      "timestamp": "2026-02-28T20:32:19.367273"
    },
    {
      "directive": "GROW",
      "avg_score": 548.5,
      "timestamp": "2026-02-28T20:32:24.755074"
    },
    {
      "directive": "GROW",
      "avg_score": 548.5,
      "timestamp": "2026-02-28T20:32:30.217609"
    },
    {
      "directive": "GROW",
      "avg_score": 548.5,
      "timestamp": "2026-02-28T20:32:35.698813"
    },
    {
      "directive": "GROW",
      "avg_score": 548.5,
      "timestamp": "2026-02-28T20:32:41.158458"
    }
  ],
  "generation": 592,
  "last": {
    "directive": "GROW",
    "meaning": "Platform mature \u2014 expand to new domains, increase scope",
    "reasoning": [
      "Growth criteria met: 4/5"
    ],
    "hormone_emitted": "growth_hormone",
    "organism": {
      "avg_score": 548.5,
      "domains": 105,
      "balance": 0.99,
      "pain_level": 0.2888095238095244,
      "stagnation": 0,
      "phase": "emergency"
    },
    "active_hormones": {
      "serotonin": {
        "count": 20,
        "avg_intensity": 0.99,
        "top_context": {
          "avg_score": 548.5,
          "stddev": 0.5,
          "balance_score": 0.99,
          "message": "Organism in balance \u2014 steady growth"
        }
      }
    },
    "next_question": "Why does dental score 580 \u2014 specifically what is '['wu_wei_flow', 'offline_first', 'today_focus', 'domain_color', 'no_login_wall']' doing for the user?",
    "next_transfer": null,
    "next_evolution_priority": null,
    "generated_at": "2026-02-28T20:32:41.158431"
  },
  "current_domains": 105,
  "target_domains": 108,
  "unbuilt_count": 3
}