{
  "id": "35f46a054559",
  "generation": 6836,
  "created_at": "2026-03-02T06:21:50.459353",
  "problem_id": "co2_capture_catalyst",
  "problem": "What catalyst efficiently converts atmospheric CO2 to useful compounds at ambient conditions?",
  "domain": "environment",
  "population": 8000000000,
  "urgency": 0.95,
  "mechanism": "Bioelectrochemical system for pollutant conversion",
  "hypothesis": "Bioelectrochemical system for pollutant conversion may resolve What catalyst efficiently converts atmospheric CO2 to useful compounds at ambient conditions? by activating at the systems level.",
  "experiment": {
    "type": "Sensor network monitoring",
    "duration_months": 9,
    "estimated_cost_usd": 94485,
    "falsifiable": true,
    "control_required": true,
    "blinding": "single-blind",
    "sample_size": null,
    "outcome_measure": "validated scale",
    "protocol": "Sensor network monitoring with 9 month follow-up. Control group receives placebo/sham."
  },
  "impact": {
    "lives_impacted": 3631780715,
    "quality_of_life_gain_pct": 50,
    "years_of_benefit": 19,
    "economic_value_usd": 181589035750000
  },
  "confidence": 0.43877818682475445,
  "wisdom": "We cannot solve problems with the same thinking that created them. \u2014 Einstein paraphrase",
  "status": "proposed"
}