{
  "id": "a9cfafe41228",
  "generation": 8622,
  "created_at": "2026-03-01T05:39:27.089667",
  "problem_id": "fusion_ignition",
  "problem": "How to achieve sustained net-positive nuclear fusion at commercial scale?",
  "domain": "physics",
  "population": 8000000000,
  "urgency": 0.85,
  "mechanism": "Quantum tunneling through energy barrier",
  "hypothesis": "If Quantum tunneling through energy barrier is applied to at, then function improves will occur because prior evidence supports this pathway.",
  "experiment": {
    "type": "Spectroscopic analysis",
    "duration_months": 11,
    "estimated_cost_usd": 255202,
    "falsifiable": true,
    "control_required": true,
    "blinding": "single-blind",
    "sample_size": null,
    "outcome_measure": "quantitative biomarker",
    "protocol": "Spectroscopic analysis with 11 month follow-up. Control group receives placebo/sham."
  },
  "impact": {
    "lives_impacted": 1553503686,
    "quality_of_life_gain_pct": 60,
    "years_of_benefit": 23,
    "economic_value_usd": 93210221160000
  },
  "confidence": 0.3176714240603193,
  "wisdom": "Real knowledge is to know the extent of one's ignorance. \u2014 Confucius",
  "status": "proposed"
}