{
  "id": "a9bb2f933b14",
  "generation": 5868,
  "created_at": "2026-03-01T05:31:35.394564",
  "problem_id": "hydrogen_storage",
  "problem": "What material stores hydrogen fuel at high density without safety risk?",
  "domain": "materials",
  "population": 3000000000,
  "urgency": 0.85,
  "mechanism": "Self-assembled monolayer for surface functionalization",
  "hypothesis": "The key to What material stores hydrogen fuel at high density without safety risk? is Self-assembled monolayer for surface functionalization \u2014 specifically Self-assembled monolayer for \u2014 which would help 3,000,000,000 people affected.",
  "experiment": {
    "type": "Synthesis and characterization",
    "duration_months": 7,
    "estimated_cost_usd": 132033,
    "falsifiable": true,
    "control_required": true,
    "blinding": "single-blind",
    "sample_size": null,
    "outcome_measure": "quantitative biomarker",
    "protocol": "Synthesis and characterization with 7 month follow-up. Control group receives placebo/sham."
  },
  "impact": {
    "lives_impacted": 488921885,
    "quality_of_life_gain_pct": 20,
    "years_of_benefit": 16,
    "economic_value_usd": 9778437700000
  },
  "confidence": 0.6717771604461136,
  "wisdom": "Real knowledge is to know the extent of one's ignorance. \u2014 Confucius",
  "status": "proposed"
}