{
  "id": "e915d0148b15",
  "generation": 4143,
  "created_at": "2026-03-02T06:12:49.427631",
  "problem_id": "solar_energy_storage",
  "problem": "How to store solar energy at grid scale without chemical battery degradation?",
  "domain": "physics",
  "population": 3000000000,
  "urgency": 0.9,
  "mechanism": "Electromagnetic induction in moving biological tissue",
  "hypothesis": "How to store solar energy at grid scale without chemical battery degradation? remains unsolved because previous research missed the role of Electromagnetic. Electromagnetic induction in moving biological tissue directly addresses this.",
  "experiment": {
    "type": "Bench-top proof of concept",
    "duration_months": 1,
    "estimated_cost_usd": 22165,
    "falsifiable": true,
    "control_required": true,
    "blinding": "single-blind",
    "sample_size": null,
    "outcome_measure": "quantitative biomarker",
    "protocol": "Bench-top proof of concept with 1 month follow-up. Control group receives placebo/sham."
  },
  "impact": {
    "lives_impacted": 589178351,
    "quality_of_life_gain_pct": 90,
    "years_of_benefit": 9,
    "economic_value_usd": 53026051590000
  },
  "confidence": 0.5088507686124242,
  "wisdom": "In the beginner's mind there are many possibilities. In the expert's mind there are few. \u2014 Shunryu Suzuki",
  "status": "proposed"
}