{
  "id": "ac8c0c9dafa4",
  "generation": 4033,
  "created_at": "2026-03-01T05:28:01.907554",
  "problem_id": "drug_discovery_speed",
  "problem": "How to predict drug-receptor binding affinity from molecular structure without wet lab?",
  "domain": "computing",
  "population": 8000000000,
  "urgency": 0.9,
  "mechanism": "Neuromorphic spike-timing dependent plasticity",
  "hypothesis": "The key to How to predict drug-receptor binding affinity from molecular structure without wet lab? is Neuromorphic spike-timing dependent plasticity \u2014 specifically Neuromorphic spike-timing dependent \u2014 which would help 8,000,000,000 people affected.",
  "experiment": {
    "type": "Benchmark on standard dataset",
    "duration_months": 2,
    "estimated_cost_usd": 7783,
    "falsifiable": true,
    "control_required": true,
    "blinding": "single-blind",
    "sample_size": null,
    "outcome_measure": "validated scale",
    "protocol": "Benchmark on standard dataset with 2 month follow-up. Control group receives placebo/sham."
  },
  "impact": {
    "lives_impacted": 1283040997,
    "quality_of_life_gain_pct": 50,
    "years_of_benefit": 25,
    "economic_value_usd": 64152049850000
  },
  "confidence": 0.38648154913278576,
  "wisdom": "If you want to find the secrets of the universe, think in terms of energy, frequency and vibration. \u2014 Tesla",
  "status": "proposed"
}