{
  "id": "f753ff33d48c",
  "generation": 382,
  "created_at": "2026-03-01T19:45:48.868402",
  "problem_id": "chronic_fatigue_cause",
  "problem": "What causes chronic fatigue syndrome \u2014 no biomarker or mechanism identified",
  "domain": "biology",
  "population": 17000000,
  "urgency": 0.8,
  "mechanism": "Epigenetic methylation/demethylation of regulatory region",
  "hypothesis": "What causes chronic fatigue syndrome \u2014 no biomarker or mechanism identified remains unsolved because previous research missed the role of Epigenetic. Epigenetic methylation/demethylation of regulatory region directly addresses this.",
  "experiment": {
    "type": "In vitro cell culture assay",
    "duration_months": 7,
    "estimated_cost_usd": 342291,
    "falsifiable": true,
    "control_required": true,
    "blinding": "double-blind",
    "sample_size": 264,
    "outcome_measure": "quantitative biomarker",
    "protocol": "In vitro cell culture assay with 7 month follow-up. Control group receives placebo/sham."
  },
  "impact": {
    "lives_impacted": 12386853,
    "quality_of_life_gain_pct": 70,
    "years_of_benefit": 28,
    "economic_value_usd": 867079710000
  },
  "confidence": 0.4474227532863537,
  "wisdom": "What we observe is not nature itself but nature exposed to our method of questioning. \u2014 Heisenberg",
  "status": "proposed"
}