{
  "id": "104af1c40a1b",
  "generation": 8701,
  "created_at": "2026-03-01T05:39:44.831759",
  "problem_id": "solar_energy_storage",
  "problem": "How to store solar energy at grid scale without chemical battery degradation?",
  "domain": "physics",
  "population": 3000000000,
  "urgency": 0.9,
  "mechanism": "Casimir effect between nanoscale surfaces",
  "hypothesis": "Combining Casimir effect between nanoscale surfaces with current standard of care could unlock function improves by addressing existing therapies only treat symptoms.",
  "experiment": {
    "type": "Spectroscopic analysis",
    "duration_months": 6,
    "estimated_cost_usd": 117822,
    "falsifiable": true,
    "control_required": true,
    "blinding": "single-blind",
    "sample_size": null,
    "outcome_measure": "quantitative biomarker",
    "protocol": "Spectroscopic analysis with 6 month follow-up. Control group receives placebo/sham."
  },
  "impact": {
    "lives_impacted": 1427651156,
    "quality_of_life_gain_pct": 30,
    "years_of_benefit": 25,
    "economic_value_usd": 42829534680000
  },
  "confidence": 0.584466997165143,
  "wisdom": "Nature uses only the longest threads to weave her patterns. \u2014 Richard Feynman",
  "status": "proposed"
}