{
  "id": "a18059895585",
  "generation": 1121,
  "created_at": "2026-03-02T05:53:47.679302",
  "problem_id": "soil_microbiome_restore",
  "problem": "How to restore depleted agricultural soil microbiome rapidly at scale?",
  "domain": "environment",
  "population": 500000000,
  "urgency": 0.9,
  "mechanism": "Biochar amendment for soil carbon sequestration",
  "hypothesis": "If Biochar amendment for soil carbon sequestration is applied to rapidly, then function improves will occur because prior evidence supports this pathway.",
  "experiment": {
    "type": "Life cycle assessment",
    "duration_months": 1,
    "estimated_cost_usd": 10570,
    "falsifiable": true,
    "control_required": true,
    "blinding": "single-blind",
    "sample_size": null,
    "outcome_measure": "validated scale",
    "protocol": "Life cycle assessment with 1 month follow-up. Control group receives placebo/sham."
  },
  "impact": {
    "lives_impacted": 162907313,
    "quality_of_life_gain_pct": 70,
    "years_of_benefit": 5,
    "economic_value_usd": 11403511910000
  },
  "confidence": 0.7076046178563362,
  "wisdom": "Nature uses only the longest threads to weave her patterns. \u2014 Richard Feynman",
  "status": "proposed"
}