{
  "id": "3e5b733a01de",
  "generation": 6121,
  "created_at": "2026-03-01T05:32:08.071128",
  "problem_id": "depression_neurobiology",
  "problem": "What is the actual neurobiological mechanism of depression \u2014 serotonin alone is insufficient",
  "domain": "neuroscience",
  "population": 280000000,
  "urgency": 0.9,
  "mechanism": "Synaptic plasticity modulation via NMDA receptor",
  "hypothesis": "Synaptic plasticity modulation via NMDA receptor may resolve What is the actual neurobiological mechanism of depression \u2014 serotonin alone is insufficient by activating at the systems level.",
  "experiment": {
    "type": "Human TMS-EEG study",
    "duration_months": 17,
    "estimated_cost_usd": 560371,
    "falsifiable": true,
    "control_required": true,
    "blinding": "double-blind",
    "sample_size": 412,
    "outcome_measure": "validated scale",
    "protocol": "Human TMS-EEG study with 17 month follow-up. Control group receives placebo/sham."
  },
  "impact": {
    "lives_impacted": 124627513,
    "quality_of_life_gain_pct": 10,
    "years_of_benefit": 11,
    "economic_value_usd": 1246275130000
  },
  "confidence": 0.6051609477914909,
  "wisdom": "We cannot solve problems with the same thinking that created them. \u2014 Einstein paraphrase",
  "status": "proposed"
}