{
  "id": "d8402ed71672",
  "generation": 1129,
  "created_at": "2026-03-02T05:53:51.910679",
  "problem_id": "alzheimers_mechanism",
  "problem": "Why do amyloid plaques form in Alzheimer's and can they be cleared?",
  "domain": "biology",
  "population": 55000000,
  "urgency": 0.95,
  "mechanism": "Telomerase activation/inhibition in target cells",
  "hypothesis": "The key to Why do amyloid plaques form in Alzheimer's and can they be cleared? is Telomerase activation/inhibition in target cells \u2014 specifically Telomerase activation/inhibition in \u2014 which would help 55,000,000 people affected.",
  "experiment": {
    "type": "Retrospective cohort analysis",
    "duration_months": 15,
    "estimated_cost_usd": 739983,
    "falsifiable": true,
    "control_required": true,
    "blinding": "double-blind",
    "sample_size": 387,
    "outcome_measure": "quantitative biomarker",
    "protocol": "Retrospective cohort analysis with 15 month follow-up. Control group receives placebo/sham."
  },
  "impact": {
    "lives_impacted": 23837092,
    "quality_of_life_gain_pct": 20,
    "years_of_benefit": 27,
    "economic_value_usd": 476741840000
  },
  "confidence": 0.46180732833849725,
  "wisdom": "To know that you do not know is the best. \u2014 Lao Tzu",
  "status": "proposed"
}