{
  "id": "703479d98625",
  "generation": 8200,
  "created_at": "2026-03-01T05:38:03.547020",
  "problem_id": "alzheimers_mechanism",
  "problem": "Why do amyloid plaques form in Alzheimer's and can they be cleared?",
  "domain": "biology",
  "population": 55000000,
  "urgency": 0.95,
  "mechanism": "Mitochondrial membrane potential modulation",
  "hypothesis": "Mitochondrial membrane potential modulation may resolve Why do amyloid plaques form in Alzheimer's and can they be cleared? by activating at the molecular level.",
  "experiment": {
    "type": "Human organoid model",
    "duration_months": 15,
    "estimated_cost_usd": 607054,
    "falsifiable": true,
    "control_required": true,
    "blinding": "double-blind",
    "sample_size": 387,
    "outcome_measure": "quantitative biomarker",
    "protocol": "Human organoid model with 15 month follow-up. Control group receives placebo/sham."
  },
  "impact": {
    "lives_impacted": 21059380,
    "quality_of_life_gain_pct": 20,
    "years_of_benefit": 11,
    "economic_value_usd": 421187600000
  },
  "confidence": 0.354043650216933,
  "wisdom": "Real knowledge is to know the extent of one's ignorance. \u2014 Confucius",
  "status": "proposed"
}