{
  "id": "006c25688d1f",
  "generation": 352,
  "created_at": "2026-03-02T06:04:38.134473",
  "problem_id": "quantum_decoherence",
  "problem": "Why does quantum superposition collapse \u2014 can decoherence be prevented at scale?",
  "domain": "physics",
  "population": 8000000000,
  "urgency": 0.7,
  "mechanism": "Plasma confinement via magnetic mirror geometry",
  "hypothesis": "The key to Why does quantum superposition collapse \u2014 can decoherence be prevented at scale? is Plasma confinement via magnetic mirror geometry \u2014 specifically Plasma confinement via \u2014 which would help 8,000,000,000 people affected.",
  "experiment": {
    "type": "Bench-top proof of concept",
    "duration_months": 9,
    "estimated_cost_usd": 182553,
    "falsifiable": true,
    "control_required": true,
    "blinding": "single-blind",
    "sample_size": null,
    "outcome_measure": "quantitative biomarker",
    "protocol": "Bench-top proof of concept with 9 month follow-up. Control group receives placebo/sham."
  },
  "impact": {
    "lives_impacted": 2277167035,
    "quality_of_life_gain_pct": 40,
    "years_of_benefit": 17,
    "economic_value_usd": 91086681400000
  },
  "confidence": 0.6893456149904871,
  "wisdom": "We cannot solve problems with the same thinking that created them. \u2014 Einstein paraphrase",
  "status": "proposed"
}