{
  "id": "a3499d582591",
  "generation": 75,
  "created_at": "2026-03-02T06:04:16.315592",
  "problem_id": "wound_regeneration",
  "problem": "Why can salamanders regenerate limbs but humans cannot \u2014 what gene pathway?",
  "domain": "biology",
  "population": 2100000,
  "urgency": 0.75,
  "mechanism": "Viral vector delivery of therapeutic gene",
  "hypothesis": "If Viral vector delivery of therapeutic gene is applied to what, then function improves will occur because prior evidence supports this pathway.",
  "experiment": {
    "type": "Retrospective cohort analysis",
    "duration_months": 19,
    "estimated_cost_usd": 809502,
    "falsifiable": true,
    "control_required": true,
    "blinding": "double-blind",
    "sample_size": 435,
    "outcome_measure": "quantitative biomarker",
    "protocol": "Retrospective cohort analysis with 19 month follow-up. Control group receives placebo/sham."
  },
  "impact": {
    "lives_impacted": 890160,
    "quality_of_life_gain_pct": 80,
    "years_of_benefit": 6,
    "economic_value_usd": 71212800000
  },
  "confidence": 0.39583288392548377,
  "wisdom": "In the beginner's mind there are many possibilities. In the expert's mind there are few. \u2014 Shunryu Suzuki",
  "status": "proposed"
}