{
  "id": "fb60cdf63117",
  "generation": 7540,
  "created_at": "2026-03-01T05:36:01.842837",
  "problem_id": "addiction_rewiring",
  "problem": "Can addiction-related neural pathway changes be reversed without withdrawal?",
  "domain": "neuroscience",
  "population": 21000000,
  "urgency": 0.9,
  "mechanism": "Cortical spreading depression mechanism in migraine",
  "hypothesis": "Can addiction-related neural pathway changes be reversed without withdrawal? remains unsolved because previous research missed the role of Cortical. Cortical spreading depression mechanism in migraine directly addresses this.",
  "experiment": {
    "type": "Longitudinal patient cohort",
    "duration_months": 10,
    "estimated_cost_usd": 249522,
    "falsifiable": true,
    "control_required": true,
    "blinding": "double-blind",
    "sample_size": 316,
    "outcome_measure": "validated scale",
    "protocol": "Longitudinal patient cohort with 10 month follow-up. Control group receives placebo/sham."
  },
  "impact": {
    "lives_impacted": 8681663,
    "quality_of_life_gain_pct": 60,
    "years_of_benefit": 17,
    "economic_value_usd": 520899780000
  },
  "confidence": 0.7295415559575884,
  "wisdom": "Nature uses only the longest threads to weave her patterns. \u2014 Richard Feynman",
  "status": "proposed"
}