{
  "id": "c9b8acc137d5",
  "generation": 2923,
  "created_at": "2026-03-02T06:09:39.537117",
  "problem_id": "chronic_pain_central",
  "problem": "How does central sensitization maintain chronic pain without tissue damage?",
  "domain": "neuroscience",
  "population": 50000000,
  "urgency": 0.9,
  "mechanism": "Dopamine/serotonin reuptake inhibition with specificity",
  "hypothesis": "The key to How does central sensitization maintain chronic pain without tissue damage? is Dopamine/serotonin reuptake inhibition with specificity \u2014 specifically Dopamine/serotonin reuptake inhibition \u2014 which would help 50,000,000 people affected.",
  "experiment": {
    "type": "fMRI connectivity study",
    "duration_months": 17,
    "estimated_cost_usd": 584157,
    "falsifiable": true,
    "control_required": true,
    "blinding": "double-blind",
    "sample_size": 412,
    "outcome_measure": "validated scale",
    "protocol": "fMRI connectivity study with 17 month follow-up. Control group receives placebo/sham."
  },
  "impact": {
    "lives_impacted": 33379944,
    "quality_of_life_gain_pct": 20,
    "years_of_benefit": 15,
    "economic_value_usd": 667598880000
  },
  "confidence": 0.3017157099954186,
  "wisdom": "We cannot solve problems with the same thinking that created them. \u2014 Einstein paraphrase",
  "status": "proposed"
}