{
  "id": "24a539155356",
  "generation": 702,
  "created_at": "2026-03-02T05:50:44.933333",
  "problem_id": "bone_scaffold_material",
  "problem": "What synthetic material perfectly mimics bone's mechanical and biological properties?",
  "domain": "materials",
  "population": 10000000,
  "urgency": 0.85,
  "mechanism": "Liquid crystal elastomer actuation",
  "hypothesis": "Combining Liquid crystal elastomer actuation with current standard of care could unlock function improves by addressing existing therapies only treat symptoms.",
  "experiment": {
    "type": "Mechanical testing (tensile, fatigue)",
    "duration_months": 10,
    "estimated_cost_usd": 174932,
    "falsifiable": true,
    "control_required": true,
    "blinding": "single-blind",
    "sample_size": null,
    "outcome_measure": "validated scale",
    "protocol": "Mechanical testing (tensile, fatigue) with 10 month follow-up. Control group receives placebo/sham."
  },
  "impact": {
    "lives_impacted": 7134887,
    "quality_of_life_gain_pct": 20,
    "years_of_benefit": 13,
    "economic_value_usd": 142697740000
  },
  "confidence": 0.35119307257029947,
  "wisdom": "Nature uses only the longest threads to weave her patterns. \u2014 Richard Feynman",
  "status": "proposed"
}