{
  "id": "9ca5ca44d59e",
  "generation": 7574,
  "created_at": "2026-03-01T05:36:08.316502",
  "problem_id": "plastic_biodegradation",
  "problem": "What enzyme or organism efficiently degrades all plastic types at scale?",
  "domain": "materials",
  "population": 8000000000,
  "urgency": 0.9,
  "mechanism": "Bacteriophage surface display for targeting",
  "hypothesis": "Bacteriophage surface display for targeting may resolve What enzyme or organism efficiently degrades all plastic types at scale? by activating at the molecular level.",
  "experiment": {
    "type": "In vitro biocompatibility assay",
    "duration_months": 29,
    "estimated_cost_usd": 406025,
    "falsifiable": true,
    "control_required": true,
    "blinding": "single-blind",
    "sample_size": null,
    "outcome_measure": "validated scale",
    "protocol": "In vitro biocompatibility assay with 29 month follow-up. Control group receives placebo/sham."
  },
  "impact": {
    "lives_impacted": 2036263615,
    "quality_of_life_gain_pct": 80,
    "years_of_benefit": 22,
    "economic_value_usd": 162901089200000
  },
  "confidence": 0.7100310328648077,
  "wisdom": "In the beginner's mind there are many possibilities. In the expert's mind there are few. \u2014 Shunryu Suzuki",
  "status": "proposed"
}