{
  "id": "68511628d041",
  "generation": 9439,
  "created_at": "2026-03-01T05:42:53.180019",
  "problem_id": "quantum_decoherence",
  "problem": "Why does quantum superposition collapse \u2014 can decoherence be prevented at scale?",
  "domain": "physics",
  "population": 8000000000,
  "urgency": 0.7,
  "mechanism": "Resonant inductive coupling for wireless power",
  "hypothesis": "Why does quantum superposition collapse \u2014 can decoherence be prevented at scale? remains unsolved because previous research missed the role of Resonant. Resonant inductive coupling for wireless power directly addresses this.",
  "experiment": {
    "type": "Materials characterization (XRD, SEM)",
    "duration_months": 4,
    "estimated_cost_usd": 76880,
    "falsifiable": true,
    "control_required": true,
    "blinding": "single-blind",
    "sample_size": null,
    "outcome_measure": "quantitative biomarker",
    "protocol": "Materials characterization (XRD, SEM) with 4 month follow-up. Control group receives placebo/sham."
  },
  "impact": {
    "lives_impacted": 3326153917,
    "quality_of_life_gain_pct": 30,
    "years_of_benefit": 5,
    "economic_value_usd": 99784617510000
  },
  "confidence": 0.713005263898657,
  "wisdom": "The impediment to action advances action. What stands in the way becomes the way. \u2014 Marcus Aurelius",
  "status": "proposed"
}