{
  "id": "c0e00ae5",
  "name": "PulseLight",
  "generation": 48635,
  "created_at": "2026-02-28T21:55:06.210338",
  "pain": "depression",
  "population": 21000000,
  "problem": "21M with major depression \u2014 no passive monitoring or early warning device",
  "physics": "photobiomodulation",
  "physics_desc": "Specific light wavelengths stimulate cell function",
  "physics_proven": true,
  "comparable_devices": [
    "Red light therapy",
    "Laser therapy"
  ],
  "form_factor": "light therapy glasses",
  "complexity": 10,
  "specs": {
    "power_watts": 0.0407,
    "size_cm": 6.1,
    "cost_usd": 161.98,
    "battery_hours": 69.2
  },
  "edge_deployable": true,
  "chip_note": "Phoenix chip (131072x131072, neuromorphic) enables on-device AI inference at 20.0GHz. No cloud. Fully private.",
  "companion_app": "MindSpace",
  "companion_domain": "mental_wellness",
  "wisdom_score": 100,
  "wisdom_criteria": {
    "proven_physics": true,
    "affordable": true,
    "reaches_millions": true,
    "edge_deployable": true,
    "has_companion_app": true,
    "chip_enhanced": true
  },
  "total_score": 100,
  "peoples_charter": true
}